{
  "version": "7",
  "dialect": "postgresql",
  "entries": [
    {
      "idx": 0,
      "version": "7",
      "when": 1756595262261,
      "tag": "0000_magenta_morlun",
      "breakpoints": true
    },
    {
      "idx": 1,
      "version": "7",
      "when": 1756861988534,
      "tag": "0001_useful_post",
      "breakpoints": true
    },
    {
      "idx": 2,
      "version": "7",
      "when": 1756999391377,
      "tag": "0002_sweet_hercules",
      "breakpoints": true
    },
    {
      "idx": 3,
      "version": "7",
      "when": 1757195476883,
      "tag": "0003_yummy_rogue",
      "breakpoints": true
    },
    {
      "idx": 4,
      "version": "7",
      "when": 1757426035154,
      "tag": "0004_nervous_tombstone",
      "breakpoints": true
    },
    {
      "idx": 5,
      "version": "7",
      "when": 1757530581020,
      "tag": "0005_rainy_tarantula",
      "breakpoints": true
    }
  ]
}